cos/__init__.py
cos/cos.py
monsoon_upload_cos-0.1.0.dist-info/LICENSE
monsoon_upload_cos-0.1.0.dist-info/METADATA
monsoon_upload_cos-0.1.0.dist-info/WHEEL
monsoon_upload_cos-0.1.0.dist-info/entry_points.txt
monsoon_upload_cos-0.1.0.dist-info/top_level.txt
monsoon_upload_cos-0.1.0.dist-info/RECORD
