Metadata-Version: 2.1
Name: monsoon-upload-cos
Version: 0.1.0
Summary: Monsoon plug-in for IBM Cloud Object Storage uploads.
Home-page: https://github.ibm.com/apset/monsoon
Author: Michael Lin
Author-email: michael.lin1@ibm.com
License: IBM
Platform: UNKNOWN
Classifier: Environment :: Console
Classifier: Intended Audience :: Developers
Classifier: Intended Audience :: System Administrators
Classifier: Environment :: MacOS X
Classifier: Operating System :: POSIX :: Linux
Classifier: Topic :: Database
Classifier: Topic :: System :: Archiving :: Backup
Classifier: Topic :: Utilities
Requires-Dist: monsoon-cli (>=0.1.7)
Requires-Dist: ibm-cos-sdk (>=2.4.4)
